carlib/__init__.py
carlib/checkpoints.py
carlib/cli.py
carlib/dataset_to_car.py
carlib/decode.py
carlib/loaders.py
carlib/setup.py
carlib/transforms.py
carlib/configs/README.md
carlib/configs/audio_config.yaml
carlib/configs/image_config.yaml
carlib/configs/video_config.yaml
rightsify_carlib-1.0.0.dist-info/licenses/LICENSE
rightsify_carlib-1.0.0.dist-info/METADATA
rightsify_carlib-1.0.0.dist-info/WHEEL
rightsify_carlib-1.0.0.dist-info/entry_points.txt
rightsify_carlib-1.0.0.dist-info/top_level.txt
rightsify_carlib-1.0.0.dist-info/RECORD
