Metadata-Version: 2.4
Name: rightsify-carlib
Version: 1.0.0
Summary: Dataset to CAR format conversion library and CLI tool for efficient neural network training
Author-email: Rightsify <dev@rightsify.com>
Maintainer-email: Rightsify Development Team <dev@rightsify.com>
License: MIT License
Project-URL: Homepage, https://github.com/rightsify/carlib
Project-URL: Bug Reports, https://github.com/rightsify/carlib/issues
Project-URL: Source, https://github.com/rightsify/carlib
Project-URL: Documentation, https://github.com/rightsify/carlib/blob/main/README.md
Project-URL: Repository, https://github.com/rightsify/carlib.git
Project-URL: Changelog, https://github.com/rightsify/carlib/blob/main/CHANGELOG.md
Keywords: machine learning,neural networks,dataset conversion,car format,data preprocessing,audio processing,image processing,video processing,webdataset,hdf5,tfrecord,encodec,compression
Classifier: Development Status :: 4 - Beta
Classifier: Intended Audience :: Developers
Classifier: Intended Audience :: Science/Research
Classifier: Intended Audience :: Information Technology
Classifier: License :: OSI Approved :: MIT License
Classifier: Operating System :: OS Independent
Classifier: Operating System :: POSIX :: Linux
Classifier: Operating System :: MacOS :: MacOS X
Classifier: Operating System :: Microsoft :: Windows
Classifier: Programming Language :: Python :: 3
Classifier: Programming Language :: Python :: 3.8
Classifier: Programming Language :: Python :: 3.9
Classifier: Programming Language :: Python :: 3.10
Classifier: Programming Language :: Python :: 3.11
Classifier: Programming Language :: Python :: 3.12
Classifier: Programming Language :: Python :: 3 :: Only
Classifier: Topic :: Scientific/Engineering :: Artificial Intelligence
Classifier: Topic :: Software Development :: Libraries :: Python Modules
Classifier: Topic :: Multimedia :: Sound/Audio
Classifier: Topic :: Multimedia :: Graphics
Classifier: Topic :: Multimedia :: Video
Classifier: Topic :: System :: Archiving :: Compression
Classifier: Topic :: Utilities
Requires-Python: >=3.8
License-File: LICENSE
Requires-Dist: torch>=1.9.0
Requires-Dist: torchaudio>=0.9.0
Requires-Dist: transformers>=4.20.0
Requires-Dist: PyYAML>=5.4.0
Requires-Dist: tqdm>=4.60.0
Requires-Dist: numpy>=1.19.0
Provides-Extra: webdataset
Requires-Dist: webdataset>=0.2.0; extra == "webdataset"
Provides-Extra: hdf5
Requires-Dist: h5py>=3.0.0; extra == "hdf5"
Provides-Extra: tfrecord
Requires-Dist: tensorflow>=2.8.0; extra == "tfrecord"
Provides-Extra: all
Requires-Dist: webdataset>=0.2.0; extra == "all"
Requires-Dist: h5py>=3.0.0; extra == "all"
Requires-Dist: tensorflow>=2.8.0; extra == "all"
Provides-Extra: dev
Requires-Dist: pytest>=6.0.0; extra == "dev"
Requires-Dist: pytest-cov>=2.10.0; extra == "dev"
Requires-Dist: black>=21.0.0; extra == "dev"
Requires-Dist: flake8>=3.8.0; extra == "dev"
Requires-Dist: mypy>=0.800; extra == "dev"
Requires-Dist: twine>=3.0.0; extra == "dev"
Requires-Dist: wheel>=0.36.0; extra == "dev"
Requires-Dist: build>=0.7.0; extra == "dev"
Dynamic: license-file
